django_populate/__init__.py
django_populate/guessers.py
django_populate/populator.py
django_populate/urls.py
django_populate/templatetags/__init__.py
django_populate/templatetags/fakers.py
tests/__init__.py
tests/models.py
tests/test_populate.py
tests/test_settings.py
django_populate-0.3.2.dist-info/LICENSE.txt
django_populate-0.3.2.dist-info/METADATA
django_populate-0.3.2.dist-info/WHEEL
django_populate-0.3.2.dist-info/top_level.txt
django_populate-0.3.2.dist-info/RECORD
