Metadata-Version: 2.1
Name: django-populate
Version: 0.3.2
Summary: Django-faker uses python-faker to generate test data for Django models and templates.
Home-page: https://gitlab.com/solarliner/django-populate
Author: SolarLiner
Author-email: solarliner@gmail.com
License: MIT
Keywords: faker populate database fixtures data test django
Platform: UNKNOWN
Classifier: Development Status :: 4 - Beta
Classifier: Intended Audience :: Information Technology
Classifier: Programming Language :: Python
Classifier: Programming Language :: Python :: 3
Classifier: Topic :: Software Development :: Libraries :: Python Modules
Classifier: Topic :: Software Development :: Testing
Classifier: Topic :: Software Development :: Widget Sets
Classifier: Topic :: Utilities
Classifier: License :: OSI Approved :: MIT License
Classifier: Framework :: Django
Requires-Dist: django (==2.1.7)
Requires-Dist: faker (==1.0.2)
Requires-Dist: python-dateutil (==2.8.0)
Requires-Dist: pytz (==2018.9)
Requires-Dist: six (==1.12.0)
Requires-Dist: text-unidecode (==1.2)
